{
  "chains": {
    "base": {
      "enabled": true,
      "rpcUrl": "https://base-mainnet.g.alchemy.com/v2/your_key",
      "privateRpcUrl": "https://base-private-rpc.example",
      "privateRpcTrusted": false,
      "quoteTokens": {
        "ALT": {
          "address": "0x0000000000000000000000000000000000000010",
          "coingeckoId": "your-coingecko-token-id"
        }
      },
      "pools": []
    },
    "mainnet": {
      "enabled": false,
      "rpcUrl": "https://eth-mainnet.g.alchemy.com/v2/your_key",
      "pools": [],
      "strategy": "flash-arb",
      "flashArb": {
        "minProfitUsd": 50
      }
    }
  },
  "pricing": {
    "provider": "coingecko"
  },
  "strategy": "funded",
  "funded": {
    "targetExitPriceUsd": 0.10,
    "autoApprove": false
  },
  "flashArb": {
    "onChainSlippageFloorPercent": 1,
    "minLiquidityUsd": 100,
    "minProfitUsd": 5,
    "routes": {
      "base": {
        "quoterAddress": "0x0000000000000000000000000000000000000000",
        "uniswapV2FactoryAddress": "0x0000000000000000000000000000000000000000",
        "executors": {
          "v2v3": "0x0000000000000000000000000000000000000000",
          "v3v2": "0x0000000000000000000000000000000000000000",
          "v3v3": "0x0000000000000000000000000000000000000000"
        },
        "sources": {
          "USDC": [
            {
              "protocol": "uniswap-v2",
              "address": "0x0000000000000000000000000000000000000000"
            },
            {
              "protocol": "uniswap-v3",
              "address": "0x0000000000000000000000000000000000000000"
            }
          ]
        },
        "swapRoutes": {
          "USDC": [
            {
              "protocol": "uniswap-v3",
              "path": "0x"
            },
            {
              "protocol": "uniswap-v2",
              "path": [
                "0x0000000000000000000000000000000000000001",
                "0x0000000000000000000000000000000000000002"
              ]
            }
          ]
        }
      }
    }
  },
  "polling": {
    "idleIntervalMs": 60000,
    "activeIntervalMs": 10000,
    "profitabilityThreshold": 0.2
  },
  "dryRun": true,
  "profitMarginPercent": 5,
  "gasPriceCeilingGwei": 100,
  "healthCheckPort": 8080
}
